PythonScreenStackManager/__init__.py
PythonScreenStackManager/__main__.py
PythonScreenStackManager/constants.py
PythonScreenStackManager/example.py
PythonScreenStackManager/exceptions.py
PythonScreenStackManager/pssm_settings.py
PythonScreenStackManager/pssm_types.py
PythonScreenStackManager/tools.py
PythonScreenStackManager/config/default-keymap-en_us.json
PythonScreenStackManager/config/default-keymap-en_us_ALT.json
PythonScreenStackManager/config/default-keymap-en_us_CAPS.json
PythonScreenStackManager/devices/__init__.py
PythonScreenStackManager/devices/const.py
PythonScreenStackManager/devices/windowed.py
PythonScreenStackManager/elements/__init__.py
PythonScreenStackManager/elements/baseelements.py
PythonScreenStackManager/elements/compoundelements.py
PythonScreenStackManager/elements/constants.py
PythonScreenStackManager/elements/deviceelements.py
PythonScreenStackManager/elements/inputelements.py
PythonScreenStackManager/elements/layoutelements.py
PythonScreenStackManager/elements/menuelements.py
PythonScreenStackManager/fonts/AllertaStencil-Regular.ttf
PythonScreenStackManager/fonts/Merriweather-Bold.ttf
PythonScreenStackManager/fonts/Merriweather-Regular.ttf
PythonScreenStackManager/fonts/NotoSans-Light.ttf
PythonScreenStackManager/fonts/NotoSans-Medium.ttf
PythonScreenStackManager/fonts/NotoSans-Regular.ttf
PythonScreenStackManager/fonts/OFL.txt
PythonScreenStackManager/fonts/PoiretOne-Regular.ttf
PythonScreenStackManager/fonts/Quicksand-Bold.ttf
PythonScreenStackManager/fonts/Quicksand-Regular.ttf
PythonScreenStackManager/pssm/__init__.py
PythonScreenStackManager/pssm/screen.py
PythonScreenStackManager/pssm/styles.py
PythonScreenStackManager/pssm/util.py
PythonScreenStackManager-0.4.0.dist-info/LICENSE
PythonScreenStackManager-0.4.0.dist-info/METADATA
PythonScreenStackManager-0.4.0.dist-info/WHEEL
PythonScreenStackManager-0.4.0.dist-info/top_level.txt
PythonScreenStackManager-0.4.0.dist-info/RECORD
