Metadata-Version: 2.2
Name: PythonScreenStackManager
Version: 0.4.0
Summary: A library that generates a gui in PIL Image objects.
Author: Slalamander
License:                     GNU GENERAL PUBLIC LICENSE
Project-URL: Homepage, https://github.com/Slalamander/PythonScreenStackManager
Project-URL: source, https://github.com/Slalamander/PythonScreenStackManager
Keywords: gui,pixels,interface,MaterialDesignIcon,mdi icons
Classifier: Programming Language :: Python :: 3.9
Classifier: Programming Language :: Python :: 3.10
Classifier: Operating System :: OS Independent
Classifier: License :: OSI Approved :: GNU General Public License v3 (GPLv3)
Requires-Python: >=3.9
License-File: LICENSE
Requires-Dist: Pillow
Requires-Dist: mdi-pil>=1.1.3
